{
    "LogisticRegression": {
        "SHAP": {
            "d1_bun_min": -4.440866837527865,
            "h1_mbp_noninvasive_min": 4.158115471673015,
            "d1_heartrate_max": -3.952016196799236,
            "h1_sysbp_noninvasive_max": -3.3630373166790357,
            "h1_mbp_min": -3.2562460168867817,
            "ventilated_apache": -3.2371408399713246,
            "age": 2.9148281640722957,
            "elective_surgery": 2.6982965907925833,
            "h1_sysbp_max": 2.5985810856991205,
            "apache_3j_diagnosis": 2.156999198709635,
            "h1_heartrate_max": 2.070183240713185,
            "bun_apache": 1.8516618125261157,
            "d1_creatinine_max": 1.8015976172822266,
            "h1_mbp_noninvasive_max": 1.8000115719854552,
            "apache_post_operative": -1.7546482364693423,
            "d1_wbc_min": -1.6310705344833687,
            "apache_3j_bodysystem": 1.4830657438054669,
            "d1_hematocrit_min": 1.4638767452558317,
            "icu_admit_source": -1.451805350349158,
            "d1_albumin_min": -1.4091944449317249,
            "resprate_apache": -1.403385697153263,
            "h1_sodium_min": -1.3907600428674722,
            "d1_mbp_min": 1.3894553872044142,
            "creatinine_apache": -1.3652678520745127,
            "d1_hemaglobin_min": -1.356747690654348,
            "gcs_motor_apache": -1.299121973324785,
            "h1_bilirubin_min": 1.190252176964895,
            "h1_bilirubin_max": -1.1251295684957787,
            "d1_glucose_min": -1.052293219349619,
            "h1_sodium_max": 1.050378368046424,
            "d1_mbp_noninvasive_min": -1.0016677318181793,
            "h1_calcium_max": 0.9694085603376449,
            "d1_temp_min": 0.9628584780652406,
            "d1_sodium_max": 0.957963456654491,
            "h1_temp_max": 0.9475509999198335,
            "d1_sodium_min": -0.9330406777479032,
            "d1_potassium_min": 0.9020723920143154,
            "h1_calcium_min": -0.8471631132549988,
            "gcs_eyes_apache": -0.8445408274783736,
            "hospital_admit_source": 0.7839062084892736,
            "h1_glucose_max": 0.7787033344241847,
            "h1_mbp_max": -0.6742716895132269,
            "d1_sysbp_noninvasive_max": -0.6718638610703449,
            "h1_diasbp_min": -0.6708251888598775,
            "icu_id": 0.6670091724464193,
            "gcs_verbal_apache": -0.6586124886065267,
            "d1_mbp_noninvasive_max": 0.6512201549917377,
            "albumin_apache": -0.625624622926493,
            "h1_diasbp_max": -0.6230726639993701,
            "weight": 0.587324675945145,
            "hematocrit_apache": 0.5751792947340333,
            "hospital_id": 0.5739322906434307,
            "pre_icu_los_days": -0.5669286722165642,
            "d1_bun_max": -0.5528005332463637,
            "gender": -0.5509014762660146,
            "wbc_apache": 0.5279298213594537,
            "d1_lactate_min": -0.5062669261639148,
            "d1_albumin_max": 0.5055410784890223,
            "d1_sysbp_max": 0.4733251449175786,
            "d1_wbc_max": 0.4683667085267453,
            "d1_mbp_max": -0.4656961947980714,
            "d1_diasbp_min": 0.4597559434979837,
            "h1_creatinine_max": -0.43287560410756365,
            "h1_glucose_min": -0.4316221433380506,
            "d1_resprate_min": -0.4310988193092576,
            "h1_diasbp_noninvasive_max": -0.4085583089357263,
            "diabetes_mellitus": 0.4050868305489215,
            "apache_2_diagnosis": -0.4042909202691412,
            "d1_platelets_min": -0.38525601211187716,
            "map_apache": -0.3784964849316269,
            "h1_hco3_min": -0.36841001820221586,
            "h1_arterial_po2_max": 0.3575272157822406,
            "h1_sysbp_min": 0.35219255252696197,
            "h1_resprate_max": -0.32874942341830365,
            "fio2_apache": -0.3010641345435643,
            "h1_temp_min": 0.29923513025245485,
            "height": -0.29723494947505225,
            "h1_sysbp_noninvasive_min": -0.2759225713835751,
            "icu_type": 0.27474661063082045,
            "d1_diasbp_noninvasive_min": -0.2729932728770268,
            "h1_heartrate_min": -0.2705556365359738,
            "h1_resprate_min": 0.26510123391584206,
            "h1_creatinine_min": 0.26410794727835557,
            "h1_spo2_min": 0.2635297505284223,
            "d1_calcium_min": -0.26335907598812,
            "heart_rate_apache": 0.25755663356725683,
            "d1_bilirubin_min": -0.2550665192079337,
            "d1_creatinine_min": -0.25054010555483985,
            "d1_lactate_max": -0.24916666182996922,
            "urineoutput_apache": 0.24718258518304959,
            "d1_heartrate_min": -0.23084530326031305,
            "h1_arterial_po2_min": -0.22905504649668534,
            "h1_potassium_max": -0.21977294123699254,
            "h1_hco3_max": -0.2152417328902554,
            "d1_spo2_min": 0.2115239714616536,
            "d1_hco3_max": 0.20179604721288197,
            "h1_diasbp_noninvasive_min": 0.2011057131547347,
            "d1_arterial_pco2_max": -0.18583872385189645,
            "h1_potassium_min": 0.17785538574160464,
            "immunosuppression": -0.17456265728428938,
            "apache_2_bodysystem": -0.16800538013465185,
            "h1_wbc_max": 0.1677435831721189,
            "h1_bun_min": 0.1550544345230715,
            "glucose_apache": 0.15456538382897664,
            "h1_hemaglobin_max": 0.15324485999211263,
            "d1_diasbp_max": -0.14615334574465025,
            "d1_spo2_max": 0.14279624259132287,
            "d1_potassium_max": -0.1383274786827513,
            "h1_wbc_min": -0.13664316924198086,
            "intubated_apache": -0.12983005677064363,
            "d1_arterial_po2_min": -0.12870482526703036,
            "h1_hematocrit_max": -0.12814961232986896,
            "arf_apache": -0.12189973940480572,
            "h1_platelets_max": 0.11849458989719747,
            "d1_hematocrit_max": 0.1179134944548898,
            "h1_albumin_min": -0.11289973370396532,
            "cirrhosis": -0.11161247535671887,
            "icu_stay_type": 0.1106146092254867,
            "h1_hemaglobin_min": -0.10206841980208434,
            "d1_arterial_po2_max": -0.10037027479825106,
            "bilirubin_apache": 0.098801394404934,
            "h1_platelets_min": -0.09518153409679926,
            "d1_hemaglobin_max": -0.09385377621740676,
            "h1_albumin_max": -0.08880067582043807,
            "h1_pao2fio2ratio_max": 0.08772839917542169,
            "pao2_apache": 0.08375329549777569,
            "sodium_apache": -0.08280720857182794,
            "d1_calcium_max": -0.08061299572423643,
            "h1_arterial_ph_max": 0.07830117730817039,
            "d1_bilirubin_max": -0.07594451453174085,
            "h1_pao2fio2ratio_min": -0.06772180056230487,
            "d1_temp_max": -0.06036710176227577,
            "d1_platelets_max": -0.05924834221140456,
            "d1_sysbp_min": 0.058665790996208764,
            "d1_sysbp_noninvasive_min": 0.0548976501423755,
            "d1_diasbp_noninvasive_max": 0.05464962899048285,
            "d1_inr_max": -0.05436002011419476,
            "h1_inr_max": -0.05436002011419476,
            "h1_bun_max": 0.051266665898780504,
            "paco2_for_ph_apache": 0.04756049969885623,
            "paco2_apache": 0.04756049969885623,
            "d1_mbp_invasive_max": 0.04143195466323352,
            "d1_diasbp_invasive_max": -0.04079838536123722,
            "h1_lactate_min": -0.039821261702513974,
            "temp_apache": -0.039661825423300906,
            "d1_arterial_pco2_min": 0.03692413358287899,
            "d1_arterial_ph_max": 0.03680720303006548,
            "h1_arterial_pco2_min": -0.036613894315112694,
            "h1_hematocrit_min": 0.03044212647426635,
            "h1_inr_min": -0.02911468533792826,
            "d1_inr_min": -0.02911468533792797,
            "h1_diasbp_invasive_min": 0.027484703595626336,
            "d1_arterial_ph_min": 0.026576463735362002,
            "h1_lactate_max": 0.02578245356819697,
            "d1_hco3_min": 0.023804718970013634,
            "h1_diasbp_invasive_max": 0.02280860920048382,
            "d1_pao2fio2ratio_max": -0.0221624854915853,
            "h1_arterial_ph_min": -0.02190105838368319,
            "h1_mbp_invasive_min": -0.02156108522807198,
            "d1_resprate_max": -0.01813106651458084,
            "h1_arterial_pco2_max": -0.016297201294070012,
            "ph_apache": -0.015673652711487907,
            "bmi": 0.0138490891800694,
            "h1_mbp_invasive_max": -0.01293969014383851,
            "hepatic_failure": 0.012881719895426757,
            "d1_mbp_invasive_min": -0.011397395137623733,
            "lymphoma": -0.010073001654002165,
            "renal_function_triad_flag": -0.00997209107406011,
            "ethnicity": -0.009458866954383067,
            "h1_sysbp_invasive_min": -0.00852909211390064,
            "mods_pentad_flag": 0.00755616616295735,
            "d1_sysbp_invasive_max": 0.0068699062898005805,
            "d1_diasbp_invasive_min": 0.0064957050841288515,
            "h1_spo2_max": 0.006271306268518524,
            "aids": 0.005502427243845156,
            "leukemia": -0.005276569653591125,
            "solid_tumor_with_metastasis": 0.0029747260319426608,
            "gcs_unable_apache": -0.0016050357712699844,
            "h1_sysbp_invasive_max": 0.0014333972476413576,
            "d1_pao2fio2ratio_min": 0.001244950014091042,
            "d1_glucose_max": 0.0006868228685192781,
            "d1_sysbp_invasive_min": -4.963583101921944e-05,
            "readmission_status": 0.0
        },
        "Lime": {
            "h1_mbp_noninvasive_min": -2.5609446276198278,
            "d1_bun_min": 2.3922430088189164,
            "age": 2.274723250767657,
            "h1_mbp_min": 1.9188243092016637,
            "d1_diasbp_noninvasive_max": 1.8586124355092937,
            "h1_sysbp_noninvasive_max": 1.8197558619481295,
            "apache_3j_diagnosis": -1.78914437398595,
            "d1_lactate_min": 1.718851857456044,
            "d1_mbp_min": -1.6932158538038613,
            "h1_arterial_po2_max": -1.6520849213672948,
            "elective_surgery": -1.6397544947153957,
            "d1_heartrate_max": 1.60860229856727,
            "ventilated_apache": 1.5087691718104324,
            "h1_sysbp_max": -1.5028361247347326,
            "d1_diasbp_max": -1.452203136539473,
            "d1_hemaglobin_min": -1.3854402509020618,
            "gcs_motor_apache": -1.325637097546297,
            "d1_spo2_min": -1.3179328960762309,
            "d1_creatinine_max": -1.2985283073049243,
            "d1_sysbp_max": 1.1483797503609228,
            "apache_post_operative": 1.1461157064872673,
            "gcs_eyes_apache": -1.1406945610625092,
            "d1_sysbp_noninvasive_max": -1.1374676295389459,
            "d1_arterial_pco2_max": 1.036793803127988,
            "d1_wbc_min": 1.0351761759610552,
            "h1_wbc_min": 1.0218880817904175,
            "apache_3j_bodysystem": 1.0072606998453815,
            "h1_platelets_min": 0.9687156860607471,
            "d1_platelets_min": -0.9546770904927201,
            "d1_albumin_min": -0.9343981580455321,
            "h1_arterial_ph_max": -0.9196359846325488,
            "d1_hematocrit_min": 0.9128814133089684,
            "h1_wbc_max": -0.9117008425372843,
            "d1_bilirubin_min": 0.9063924232981659,
            "h1_calcium_max": -0.9015130474932637,
            "h1_sysbp_min": -0.8302228014398035,
            "bun_apache": -0.8225964765062034,
            "h1_platelets_max": -0.8031379933169153,
            "h1_diasbp_min": 0.7979821575096883,
            "d1_platelets_max": 0.7789787388939919,
            "creatinine_apache": 0.7741597995637219,
            "h1_sodium_max": 0.7716831308534184,
            "h1_mbp_max": 0.7698175867543811,
            "resprate_apache": 0.7607648437149024,
            "h1_sodium_min": -0.7603987365832985,
            "solid_tumor_with_metastasis": 0.7497126218690172,
            "fio2_apache": 0.744853334618769,
            "icu_admit_source": 0.7435642064411372,
            "h1_lactate_max": 0.7200498205896445,
            "d1_sodium_min": -0.7048753165736715,
            "d1_mbp_noninvasive_max": 0.6946730590840131,
            "h1_diasbp_invasive_max": -0.6932786991829853,
            "d1_lactate_max": 0.6752700791931584,
            "h1_resprate_min": 0.6744642184695306,
            "h1_potassium_max": -0.6620004593855644,
            "h1_sysbp_noninvasive_min": 0.638169511267524,
            "renal_function_triad_flag": 0.6355680419193606,
            "d1_diasbp_min": -0.6164398361745883,
            "d1_bilirubin_max": 0.6122435268144207,
            "pao2_apache": -0.57635831937218,
            "d1_spo2_max": -0.5730492107460418,
            "temp_apache": 0.5702131802216991,
            "h1_diasbp_invasive_min": 0.5669536939843935,
            "h1_mbp_noninvasive_max": -0.5667258705567563,
            "icu_stay_type": -0.5596377537502307,
            "h1_diasbp_noninvasive_max": 0.5176916288547687,
            "h1_hematocrit_max": 0.506069519306439,
            "h1_pao2fio2ratio_max": 0.5010033028611784,
            "d1_resprate_min": 0.4996412632407405,
            "d1_diasbp_invasive_max": 0.4934223277096708,
            "h1_lactate_min": -0.4879832648779222,
            "h1_arterial_po2_min": 0.4814847270528029,
            "pre_icu_los_days": 0.4770713812762683,
            "hepatic_failure": 0.4647309477273701,
            "d1_temp_min": -0.4640924577546211,
            "map_apache": 0.4605811455505247,
            "hospital_admit_source": -0.45781241657244726,
            "albumin_apache": -0.45697956177757054,
            "d1_mbp_noninvasive_min": 0.4568274267273551,
            "immunosuppression": 0.4564628910303502,
            "d1_calcium_min": 0.453029957309325,
            "d1_diasbp_noninvasive_min": 0.44829037775173475,
            "h1_sysbp_invasive_min": 0.4441187298457462,
            "h1_resprate_max": 0.44285701112963805,
            "d1_bun_max": 0.4413197117316279,
            "h1_glucose_max": -0.4388188499521916,
            "h1_arterial_pco2_min": -0.43165768419569955,
            "d1_mbp_max": -0.4274368141896375,
            "d1_hco3_max": -0.4272211448212189,
            "h1_heartrate_max": -0.4237985376396502,
            "d1_albumin_max": 0.4180485703298755,
            "leukemia": 0.4138318109191753,
            "d1_sysbp_noninvasive_min": -0.4067218420327665,
            "apache_2_diagnosis": 0.4053731870268475,
            "d1_glucose_min": 0.40404104475022623,
            "h1_calcium_min": 0.4010812356823824,
            "h1_mbp_invasive_min": 0.3994756549282684,
            "paco2_apache": -0.39751880495485487,
            "icu_type": 0.39292439184436045,
            "aids": 0.3776886119767844,
            "glucose_apache": 0.3549435606641498,
            "h1_bilirubin_min": 0.3516580488805124,
            "h1_bilirubin_max": 0.3469245661948533,
            "ph_apache": 0.34639681285374196,
            "d1_arterial_po2_max": 0.34561930422122666,
            "d1_hemaglobin_max": -0.3448470647984483,
            "h1_spo2_min": 0.3371686913570241,
            "cirrhosis": 0.32175778214036715,
            "h1_spo2_max": -0.30777819833033443,
            "gcs_verbal_apache": -0.30700521414364684,
            "d1_heartrate_min": 0.3048660553247405,
            "urineoutput_apache": -0.3038288541255221,
            "weight": -0.30164220809929715,
            "d1_resprate_max": 0.2999310004059784,
            "hematocrit_apache": 0.2944753338808409,
            "mods_pentad_flag": 0.2932833878817575,
            "h1_creatinine_min": -0.28612867883660154,
            "h1_arterial_ph_min": 0.2843741135245594,
            "hospital_id": -0.2789777589940109,
            "d1_wbc_max": -0.2774788263457645,
            "d1_pao2fio2ratio_max": -0.2608774240913829,
            "d1_sysbp_invasive_max": 0.2567946407744906,
            "h1_hco3_max": 0.25497854458971775,
            "d1_glucose_max": 0.2513527788112891,
            "gcs_unable_apache": 0.24987844151313454,
            "h1_potassium_min": 0.2435569220010388,
            "bmi": 0.241911983730637,
            "d1_pao2fio2ratio_min": -0.23380278121234102,
            "h1_diasbp_noninvasive_min": -0.23054260206450042,
            "h1_bun_max": 0.22691739836571603,
            "readmission_status": 0.22326756738657647,
            "apache_2_bodysystem": -0.22236651153847553,
            "intubated_apache": 0.21586947578741783,
            "gender": 0.21266073418040654,
            "height": 0.21023585226592917,
            "h1_pao2fio2ratio_min": -0.2042948897044066,
            "h1_diasbp_max": 0.1965562204694325,
            "ethnicity": -0.18602171102703646,
            "d1_arterial_ph_min": 0.1780190860441741,
            "h1_creatinine_max": 0.17532849148386187,
            "h1_temp_min": 0.17380050998970326,
            "h1_albumin_min": -0.1703808344952706,
            "d1_hematocrit_max": -0.16155440577336005,
            "h1_bun_min": -0.15700256907369936,
            "d1_mbp_invasive_max": -0.15550807929134372,
            "d1_potassium_min": -0.15463585902677623,
            "d1_sysbp_min": 0.15430698489730182,
            "h1_glucose_min": 0.14938775750921296,
            "d1_inr_min": 0.14424272222861595,
            "d1_calcium_max": -0.1426919681395406,
            "h1_hco3_min": -0.13049449238237126,
            "arf_apache": -0.1289985350595954,
            "heart_rate_apache": -0.1265376458709262,
            "d1_hco3_min": -0.1233737170845343,
            "d1_creatinine_min": 0.12227203520739169,
            "h1_hematocrit_min": 0.11898034073371501,
            "paco2_for_ph_apache": 0.11527711163308373,
            "diabetes_mellitus": -0.11405782201243969,
            "d1_arterial_pco2_min": -0.11402336476326073,
            "h1_hemaglobin_min": -0.11240602659795922,
            "icu_id": -0.10307761421702137,
            "h1_arterial_pco2_max": -0.10071079346890806,
            "h1_inr_min": 0.10052434723657598,
            "d1_potassium_max": -0.096255950860617,
            "lymphoma": 0.09582620389105888,
            "h1_sysbp_invasive_max": -0.09201101395789474,
            "h1_mbp_invasive_max": -0.08766765872439188,
            "h1_inr_max": 0.08043829041111639,
            "wbc_apache": -0.08037411827991184,
            "d1_arterial_ph_max": -0.07410316565028426,
            "d1_diasbp_invasive_min": 0.05096882695147917,
            "d1_sodium_max": 0.046896748781145615,
            "d1_arterial_po2_min": 0.04569311544441924,
            "d1_mbp_invasive_min": 0.03419004207045957,
            "h1_temp_max": 0.026833997877080826,
            "h1_hemaglobin_max": -0.026311090085951953,
            "bilirubin_apache": -0.021791161766766376,
            "h1_heartrate_min": -0.020990829846198624,
            "sodium_apache": 0.01620597344971564,
            "d1_sysbp_invasive_min": -0.015962806324564576,
            "h1_albumin_max": 0.013317317716295086,
            "d1_inr_max": 0.007129917074371818,
            "d1_temp_max": -0.0017201226961101378
        },
        "Inherent": {
            "h1_mbp_noninvasive_min": 4.09521112054169,
            "age": 2.9247164070180585,
            "h1_sysbp_max": 2.6373010148405895,
            "elective_surgery": 2.21851847828043,
            "h1_heartrate_max": 2.1728053668483596,
            "bun_apache": 1.8301383270166383,
            "h1_mbp_noninvasive_max": 1.820404953602913,
            "d1_creatinine_max": 1.7936510075468974,
            "d1_hematocrit_min": 1.6471056501619528,
            "apache_3j_bodysystem": 1.584462096685025,
            "d1_mbp_min": 1.4523282965381945,
            "apache_3j_diagnosis": 1.4185979410277179,
            "h1_bilirubin_min": 1.258574575928253,
            "d1_sodium_max": 1.1339680625780186,
            "d1_temp_min": 1.0082246569015392,
            "d1_potassium_min": 0.9643411244813608,
            "h1_temp_max": 0.9554524966430658,
            "h1_sodium_max": 0.9537336236723944,
            "h1_calcium_max": 0.9117743034526381,
            "h1_glucose_max": 0.7395060462675502,
            "d1_mbp_noninvasive_max": 0.7270414444285253,
            "icu_id": 0.6845095675080975,
            "hospital_admit_source": 0.6398401275355946,
            "hematocrit_apache": 0.6350608581417593,
            "hospital_id": 0.5557616445310004,
            "d1_albumin_max": 0.5142529078787453,
            "h1_arterial_po2_max": 0.47898415477768225,
            "d1_diasbp_min": 0.4755719800726769,
            "diabetes_mellitus": 0.469936799797514,
            "weight": 0.469412293538045,
            "wbc_apache": 0.4668803863453701,
            "d1_wbc_max": 0.43683709812136257,
            "h1_sysbp_min": 0.3497024901465151,
            "d1_sysbp_max": 0.3463077654043815,
            "h1_temp_min": 0.30666263201892613,
            "icu_type": 0.2912740288171436,
            "h1_creatinine_min": 0.27991786238300237,
            "heart_rate_apache": 0.259179042479627,
            "urineoutput_apache": 0.23589293169341458,
            "d1_hco3_max": 0.21921577371283554,
            "h1_resprate_min": 0.21803861570633531,
            "h1_potassium_min": 0.21170088006995016,
            "h1_spo2_min": 0.20686727311797748,
            "h1_wbc_max": 0.20537230343112725,
            "h1_diasbp_noninvasive_min": 0.18905144709508556,
            "d1_hematocrit_max": 0.18691541430665687,
            "h1_bun_min": 0.16154130800638283,
            "h1_lactate_min": 0.13980130404586352,
            "glucose_apache": 0.1380616872307484,
            "d1_platelets_max": 0.13572873160381946,
            "d1_spo2_max": 0.1315231113694828,
            "pao2_apache": 0.11951464323996866,
            "bilirubin_apache": 0.11867270992696562,
            "d1_diasbp_max": 0.11097535894497398,
            "icu_stay_type": 0.09065764869442644,
            "h1_diasbp_invasive_max": 0.08897325009092634,
            "d1_arterial_ph_max": 0.07382942169214401,
            "d1_spo2_min": 0.06973758843898374,
            "d1_arterial_ph_min": 0.06321916079592166,
            "d1_pao2fio2ratio_max": 0.058080321441898515,
            "h1_arterial_ph_max": 0.05621890015052959,
            "h1_bun_max": 0.05343436772977173,
            "h1_pao2fio2ratio_min": 0.04766072973290559,
            "d1_mbp_invasive_max": 0.042638615740398754,
            "paco2_apache": 0.03702109696989523,
            "paco2_for_ph_apache": 0.03702109696989523,
            "h1_arterial_pco2_min": 0.03329109380902693,
            "d1_pao2fio2ratio_min": 0.033130593935220616,
            "bmi": 0.029359130503285424,
            "d1_hco3_min": 0.026737126239604465,
            "d1_mbp_invasive_min": 0.024308251860918877,
            "d1_arterial_pco2_min": 0.023986926598906777,
            "h1_hemaglobin_max": 0.023327765229115532,
            "h1_arterial_pco2_max": 0.02018006377182175,
            "h1_sysbp_invasive_min": 0.019837809996604224,
            "h1_platelets_max": 0.0186465125685563,
            "h1_spo2_max": 0.013893829571943371,
            "d1_sysbp_invasive_min": 0.009872039036224262,
            "d1_sysbp_invasive_max": 0.006682814307525784,
            "h1_platelets_min": 0.004159546923061958,
            "d1_sysbp_min": 0.0032961013593615367,
            "d1_sysbp_noninvasive_min": 0.002575150935027263,
            "h1_hematocrit_min": 0.001134152155633288,
            "d1_glucose_max": 0.0006449893825093641,
            "readmission_status": 0.0,
            "aids": 0.0,
            "mods_pentad_flag": 0.0,
            "leukemia": 0.0,
            "h1_hematocrit_max": -0.0025350552196850905,
            "d1_diasbp_invasive_min": -0.0037684035194043217,
            "ethnicity": -0.0048825150887366305,
            "h1_sysbp_invasive_max": -0.00637201197366849,
            "ph_apache": -0.00879808056222086,
            "h1_hemaglobin_min": -0.009997697126047716,
            "h1_arterial_ph_min": -0.014503358634853872,
            "d1_resprate_max": -0.018308843421348964,
            "hepatic_failure": -0.022297741024082236,
            "h1_mbp_invasive_max": -0.023814443630238005,
            "cirrhosis": -0.023819503631275267,
            "lymphoma": -0.029591241138250294,
            "d1_potassium_max": -0.0325843978461048,
            "temp_apache": -0.03693502166084348,
            "d1_temp_max": -0.045142503808665246,
            "renal_function_triad_flag": -0.051650716488850945,
            "d1_calcium_max": -0.05695745067624635,
            "d1_diasbp_invasive_max": -0.0589031023325676,
            "d1_inr_min": -0.06025771264744085,
            "h1_inr_min": -0.060257712647441446,
            "h1_mbp_invasive_min": -0.06408541981216258,
            "d1_inr_max": -0.0642932046287191,
            "h1_inr_max": -0.0642932046287191,
            "d1_arterial_po2_min": -0.08725450433765085,
            "h1_diasbp_invasive_min": -0.09148851562990229,
            "h1_lactate_max": -0.09163899675415701,
            "h1_pao2fio2ratio_max": -0.09516473645494644,
            "sodium_apache": -0.0977348095740186,
            "immunosuppression": -0.10025839572025219,
            "h1_albumin_max": -0.1004261072083105,
            "d1_diasbp_noninvasive_max": -0.11008445363258779,
            "intubated_apache": -0.11533845917637353,
            "d1_bilirubin_max": -0.12369489453137644,
            "h1_albumin_min": -0.12773110405837415,
            "gcs_unable_apache": -0.13039231213554117,
            "d1_arterial_po2_max": -0.14416795640778482,
            "d1_lactate_max": -0.1462646260417736,
            "fio2_apache": -0.14720238180394207,
            "h1_wbc_min": -0.16400664861299913,
            "arf_apache": -0.1700070004406424,
            "solid_tumor_with_metastasis": -0.1946246526571344,
            "d1_calcium_min": -0.20470491013346934,
            "h1_hco3_max": -0.22122587119218282,
            "d1_heartrate_min": -0.22735112891807036,
            "h1_potassium_max": -0.2363323232168328,
            "apache_2_bodysystem": -0.2422413182677382,
            "d1_arterial_pco2_max": -0.2561658472398584,
            "h1_sysbp_noninvasive_min": -0.2748236121233422,
            "h1_heartrate_min": -0.2750741293652719,
            "d1_creatinine_min": -0.28402557693557057,
            "d1_diasbp_noninvasive_min": -0.28952921134939114,
            "height": -0.29670385673259436,
            "h1_arterial_po2_min": -0.3073030503180053,
            "d1_hemaglobin_max": -0.3609606829451711,
            "h1_resprate_max": -0.3660296654858664,
            "h1_hco3_min": -0.3774409840724891,
            "d1_lactate_min": -0.3879849905497254,
            "map_apache": -0.38819493084510037,
            "apache_2_diagnosis": -0.3942230639056743,
            "d1_bilirubin_min": -0.40129636267536284,
            "h1_glucose_min": -0.40258943122972013,
            "h1_diasbp_noninvasive_max": -0.420226980267248,
            "d1_resprate_min": -0.44855448012509835,
            "h1_creatinine_max": -0.4590701684907969,
            "d1_mbp_max": -0.5034034896357059,
            "d1_bun_max": -0.5130605141843505,
            "d1_sysbp_noninvasive_max": -0.5164204374846246,
            "gender": -0.5226461552002462,
            "d1_platelets_min": -0.5364390157935816,
            "h1_diasbp_min": -0.6397023412046109,
            "albumin_apache": -0.6450993035630674,
            "h1_diasbp_max": -0.6463954797918475,
            "h1_mbp_max": -0.6830489739966774,
            "gcs_verbal_apache": -0.6883812502532953,
            "pre_icu_los_days": -0.7006845804381008,
            "h1_calcium_min": -0.7971197911055413,
            "gcs_eyes_apache": -0.9147606197672039,
            "d1_sodium_min": -0.9593901128933694,
            "d1_mbp_noninvasive_min": -0.9640315126289729,
            "d1_glucose_min": -1.0777227547138533,
            "h1_bilirubin_max": -1.1897293155080844,
            "gcs_motor_apache": -1.3323966443613593,
            "apache_post_operative": -1.3375712719292587,
            "creatinine_apache": -1.3439216439055648,
            "h1_sodium_min": -1.3550297685794674,
            "icu_admit_source": -1.4079869371479437,
            "resprate_apache": -1.4618417182054384,
            "d1_albumin_min": -1.465095166932379,
            "d1_hemaglobin_min": -1.519048612798107,
            "d1_wbc_min": -1.647220453583686,
            "ventilated_apache": -3.093140564293961,
            "h1_mbp_min": -3.276964609954601,
            "h1_sysbp_noninvasive_max": -3.3957070963125653,
            "d1_heartrate_max": -4.272328268528343,
            "d1_bun_min": -4.419750897501385
        }
    },
    "DecisionTree": {
        "SHAP": {
            "ventilated_apache": -41.885841813037295,
            "d1_bun_min": -12.887937914140618,
            "apache_3j_diagnosis": 8.2475709203416,
            "d1_sysbp_min": -6.228265351257583,
            "d1_lactate_min": -5.4229454039848,
            "gcs_motor_apache": -4.82342881430349,
            "d1_sysbp_noninvasive_min": -4.774458623163511,
            "d1_resprate_max": -4.41954118622715,
            "age": 3.7493071700115004,
            "d1_lactate_max": -1.7495525893119985,
            "apache_2_diagnosis": 1.6128868970942856,
            "d1_temp_min": -1.5664226992900734,
            "bun_apache": -0.782847236745128,
            "d1_mbp_noninvasive_min": -0.5739270866456827,
            "gcs_eyes_apache": -0.4545731662559,
            "d1_pao2fio2ratio_max": -0.3132013588341903,
            "d1_hco3_max": -0.25959202207719945,
            "d1_arterial_ph_max": -0.10193985927601304,
            "d1_heartrate_min": -0.09866010725163117,
            "icu_id": 0.027232811912911846,
            "d1_glucose_max": 0.019866968837445143,
            "ethnicity": 0.0,
            "elective_surgery": 0.0,
            "creatinine_apache": 0.0,
            "bilirubin_apache": 0.0,
            "arf_apache": 0.0,
            "apache_post_operative": 0.0,
            "gcs_verbal_apache": 0.0,
            "glucose_apache": 0.0,
            "fio2_apache": 0.0,
            "gcs_unable_apache": 0.0,
            "intubated_apache": 0.0,
            "map_apache": 0.0,
            "paco2_apache": 0.0,
            "paco2_for_ph_apache": 0.0,
            "pao2_apache": 0.0,
            "ph_apache": 0.0,
            "heart_rate_apache": 0.0,
            "hematocrit_apache": 0.0,
            "sodium_apache": 0.0,
            "resprate_apache": 0.0,
            "urineoutput_apache": 0.0,
            "temp_apache": 0.0,
            "height": 0.0,
            "gender": 0.0,
            "icu_admit_source": 0.0,
            "icu_stay_type": 0.0,
            "weight": 0.0,
            "readmission_status": 0.0,
            "pre_icu_los_days": 0.0,
            "albumin_apache": 0.0,
            "icu_type": 0.0,
            "hospital_admit_source": 0.0,
            "hospital_id": 0.0,
            "bmi": 0.0,
            "d1_mbp_min": 0.0,
            "d1_mbp_max": 0.0,
            "d1_mbp_invasive_min": 0.0,
            "d1_mbp_invasive_max": 0.0,
            "d1_heartrate_max": 0.0,
            "d1_diasbp_noninvasive_min": 0.0,
            "d1_diasbp_noninvasive_max": 0.0,
            "d1_diasbp_min": 0.0,
            "wbc_apache": 0.0,
            "d1_diasbp_max": 0.0,
            "d1_diasbp_invasive_min": 0.0,
            "d1_diasbp_invasive_max": 0.0,
            "d1_sysbp_invasive_min": 0.0,
            "d1_spo2_max": 0.0,
            "d1_spo2_min": 0.0,
            "d1_sysbp_invasive_max": 0.0,
            "h1_diasbp_max": 0.0,
            "h1_diasbp_min": 0.0,
            "h1_diasbp_noninvasive_max": 0.0,
            "h1_diasbp_noninvasive_min": 0.0,
            "h1_heartrate_max": 0.0,
            "h1_heartrate_min": 0.0,
            "h1_mbp_invasive_max": 0.0,
            "h1_mbp_invasive_min": 0.0,
            "h1_mbp_max": 0.0,
            "h1_mbp_min": 0.0,
            "h1_mbp_noninvasive_max": 0.0,
            "d1_sysbp_max": 0.0,
            "d1_sysbp_noninvasive_max": 0.0,
            "d1_temp_max": 0.0,
            "d1_mbp_noninvasive_max": 0.0,
            "d1_resprate_min": 0.0,
            "h1_spo2_min": 0.0,
            "h1_spo2_max": 0.0,
            "h1_resprate_min": 0.0,
            "h1_resprate_max": 0.0,
            "h1_mbp_noninvasive_min": 0.0,
            "h1_sysbp_invasive_max": 0.0,
            "h1_sysbp_max": 0.0,
            "h1_sysbp_invasive_min": 0.0,
            "h1_temp_min": 0.0,
            "d1_albumin_max": 0.0,
            "d1_bilirubin_max": 0.0,
            "d1_albumin_min": 0.0,
            "h1_sysbp_noninvasive_max": 0.0,
            "h1_sysbp_noninvasive_min": 0.0,
            "h1_temp_max": 0.0,
            "h1_sysbp_min": 0.0,
            "d1_calcium_min": 0.0,
            "d1_calcium_max": 0.0,
            "d1_bun_max": 0.0,
            "d1_bilirubin_min": 0.0,
            "d1_glucose_min": 0.0,
            "d1_hco3_min": 0.0,
            "d1_creatinine_min": 0.0,
            "d1_creatinine_max": 0.0,
            "d1_hemaglobin_min": 0.0,
            "d1_hemaglobin_max": 0.0,
            "d1_hematocrit_max": 0.0,
            "d1_hematocrit_min": 0.0,
            "d1_inr_min": 0.0,
            "d1_inr_max": 0.0,
            "h1_diasbp_invasive_max": 0.0,
            "h1_diasbp_invasive_min": 0.0,
            "d1_platelets_min": 0.0,
            "d1_platelets_max": 0.0,
            "d1_potassium_max": 0.0,
            "d1_potassium_min": 0.0,
            "d1_wbc_max": 0.0,
            "d1_wbc_min": 0.0,
            "d1_sodium_max": 0.0,
            "d1_sodium_min": 0.0,
            "h1_bilirubin_max": 0.0,
            "h1_bilirubin_min": 0.0,
            "h1_bun_max": 0.0,
            "h1_bun_min": 0.0,
            "h1_calcium_max": 0.0,
            "h1_calcium_min": 0.0,
            "h1_albumin_max": 0.0,
            "h1_albumin_min": 0.0,
            "h1_glucose_max": 0.0,
            "h1_glucose_min": 0.0,
            "h1_hco3_max": 0.0,
            "h1_hco3_min": 0.0,
            "h1_hemaglobin_max": 0.0,
            "h1_hemaglobin_min": 0.0,
            "h1_hematocrit_max": 0.0,
            "h1_hematocrit_min": 0.0,
            "h1_inr_max": 0.0,
            "h1_inr_min": 0.0,
            "h1_lactate_max": 0.0,
            "h1_lactate_min": 0.0,
            "h1_platelets_max": 0.0,
            "h1_platelets_min": 0.0,
            "h1_creatinine_max": 0.0,
            "h1_creatinine_min": 0.0,
            "h1_potassium_min": 0.0,
            "h1_potassium_max": 0.0,
            "h1_wbc_max": 0.0,
            "h1_sodium_max": 0.0,
            "h1_wbc_min": 0.0,
            "d1_arterial_pco2_max": 0.0,
            "d1_arterial_pco2_min": 0.0,
            "h1_sodium_min": 0.0,
            "d1_arterial_ph_min": 0.0,
            "d1_arterial_po2_max": 0.0,
            "d1_arterial_po2_min": 0.0,
            "d1_pao2fio2ratio_min": 0.0,
            "h1_arterial_pco2_max": 0.0,
            "h1_arterial_pco2_min": 0.0,
            "h1_arterial_ph_max": 0.0,
            "h1_arterial_ph_min": 0.0,
            "h1_arterial_po2_max": 0.0,
            "h1_arterial_po2_min": 0.0,
            "h1_pao2fio2ratio_max": 0.0,
            "h1_pao2fio2ratio_min": 0.0,
            "aids": 0.0,
            "cirrhosis": 0.0,
            "diabetes_mellitus": 0.0,
            "hepatic_failure": 0.0,
            "immunosuppression": 0.0,
            "leukemia": 0.0,
            "lymphoma": 0.0,
            "solid_tumor_with_metastasis": 0.0,
            "apache_3j_bodysystem": 0.0,
            "apache_2_bodysystem": 0.0,
            "renal_function_triad_flag": 0.0,
            "mods_pentad_flag": 0.0
        },
        "Lime": {
            "ventilated_apache": 5.67230320087526,
            "d1_sysbp_min": -4.241724265819309,
            "d1_bun_min": 2.9542783479692325,
            "d1_lactate_min": 2.054818772527518,
            "d1_calcium_min": 1.7415051811133164,
            "d1_inr_min": -1.6575070654024349,
            "d1_resprate_min": 1.608707109466938,
            "apache_3j_diagnosis": -1.5555444067247328,
            "d1_creatinine_min": 1.445822337734254,
            "h1_bun_min": 1.4031205028580633,
            "wbc_apache": 1.2417017516177915,
            "d1_pao2fio2ratio_max": -1.2023711349811603,
            "ethnicity": -1.1843168204455716,
            "d1_hemaglobin_max": 1.168377650029618,
            "d1_mbp_min": 1.0984424191664226,
            "h1_arterial_ph_min": 1.0928205405567386,
            "h1_calcium_min": -1.07194110646016,
            "d1_sysbp_noninvasive_min": -1.0713242558250842,
            "d1_spo2_min": -1.0657438974436872,
            "d1_arterial_po2_min": -1.0445265251736917,
            "gcs_motor_apache": -0.9919012907814474,
            "hospital_id": -0.9830490282866589,
            "h1_potassium_max": 0.9703763239489009,
            "h1_platelets_min": -0.9623330508522144,
            "d1_calcium_max": 0.9376682273404349,
            "h1_calcium_max": -0.9328841799463181,
            "gender": -0.925990636463205,
            "h1_inr_min": 0.9164112649292168,
            "d1_platelets_max": 0.9140090453686078,
            "h1_bilirubin_max": 0.8980346830128509,
            "creatinine_apache": 0.8899707990464585,
            "pre_icu_los_days": 0.8826671291505207,
            "h1_sysbp_noninvasive_max": -0.872066790085581,
            "d1_diasbp_invasive_min": 0.8582381947253215,
            "d1_diasbp_min": 0.8455197619979075,
            "gcs_verbal_apache": -0.8425329882534,
            "d1_sysbp_invasive_min": -0.8128714793382632,
            "d1_hematocrit_min": -0.8112030452008441,
            "glucose_apache": -0.7885094751736569,
            "h1_creatinine_min": 0.7803423784700758,
            "h1_glucose_max": 0.7745520396629583,
            "d1_arterial_ph_max": -0.7721094263186303,
            "d1_mbp_noninvasive_max": -0.7324790617429454,
            "sodium_apache": -0.7231633643150074,
            "h1_mbp_noninvasive_max": -0.7205783683841825,
            "h1_mbp_invasive_max": 0.7089072533873692,
            "apache_post_operative": -0.7087710059563348,
            "icu_type": -0.7049496382840839,
            "d1_heartrate_min": 0.7032437947405169,
            "h1_temp_max": 0.6892549136407192,
            "d1_bilirubin_min": -0.6872492746912949,
            "immunosuppression": 0.6824396663891411,
            "arf_apache": 0.6564371636259466,
            "h1_heartrate_min": 0.646212487970336,
            "h1_bun_max": 0.6388887818694347,
            "h1_pao2fio2ratio_min": -0.6351410065261542,
            "d1_hco3_min": 0.6348172612276026,
            "d1_arterial_pco2_min": 0.6292237032703328,
            "h1_glucose_min": 0.6161625496937485,
            "d1_arterial_po2_max": -0.5975458648149616,
            "h1_sodium_min": -0.5955812369727229,
            "d1_potassium_max": 0.5942897641458572,
            "d1_albumin_max": -0.5854394166109326,
            "h1_heartrate_max": 0.582113471854826,
            "d1_albumin_min": -0.5815133208905604,
            "aids": -0.5796904368376165,
            "h1_mbp_max": 0.5678882145586692,
            "bmi": -0.5395396344258077,
            "weight": 0.531939823882688,
            "hepatic_failure": 0.5265740446681171,
            "d1_glucose_max": -0.5234686613840996,
            "pao2_apache": -0.5205263476668994,
            "h1_hematocrit_max": -0.5184368132329294,
            "h1_temp_min": 0.5075715557073565,
            "h1_sysbp_max": 0.5019292675085555,
            "d1_bilirubin_max": -0.5000373285918394,
            "resprate_apache": -0.497080421598535,
            "h1_pao2fio2ratio_max": 0.49268246787430214,
            "h1_resprate_max": -0.4861755189415616,
            "d1_arterial_ph_min": -0.48330062074082303,
            "urineoutput_apache": 0.4789422805791428,
            "readmission_status": 0.47384023315598195,
            "h1_diasbp_max": 0.4689037835712731,
            "d1_sodium_min": 0.46494995701560243,
            "h1_hco3_min": 0.46461808786639347,
            "h1_potassium_min": -0.463098163875491,
            "icu_stay_type": -0.4601590875200752,
            "d1_mbp_invasive_min": 0.45422625796266236,
            "h1_bilirubin_min": 0.4528451158597627,
            "d1_hco3_max": 0.44144565828638804,
            "h1_inr_max": -0.4364651437846967,
            "h1_sysbp_invasive_min": -0.43538382003619974,
            "d1_sysbp_noninvasive_max": -0.4275184760177124,
            "bilirubin_apache": -0.42645667362449347,
            "h1_sysbp_invasive_max": 0.42366213705257755,
            "h1_hemaglobin_max": -0.4095157778699497,
            "d1_sodium_max": 0.3983715573990605,
            "d1_heartrate_max": -0.397877504200773,
            "d1_creatinine_max": -0.383257831825229,
            "h1_sodium_max": -0.37216808327648987,
            "h1_lactate_max": 0.3703386957357388,
            "h1_wbc_max": 0.3691600943301974,
            "h1_arterial_po2_max": -0.36717043759850204,
            "map_apache": -0.36347359758961845,
            "apache_3j_bodysystem": 0.3402265912345907,
            "temp_apache": -0.3394726920391331,
            "h1_albumin_max": 0.3355015880187816,
            "apache_2_diagnosis": -0.33426919030255786,
            "h1_platelets_max": 0.3227012020434585,
            "d1_mbp_invasive_max": 0.3226118757686957,
            "h1_hco3_max": -0.31853977089095625,
            "h1_arterial_po2_min": 0.309965955944406,
            "mods_pentad_flag": -0.3085501107173828,
            "d1_diasbp_max": 0.3049487217494024,
            "h1_wbc_min": -0.3045165178170095,
            "bun_apache": 0.3025655850826246,
            "apache_2_bodysystem": -0.2894800412591265,
            "d1_pao2fio2ratio_min": -0.27427898333179823,
            "h1_spo2_max": 0.2712479630783548,
            "d1_glucose_min": -0.2661332375544184,
            "gcs_eyes_apache": -0.2535356867890015,
            "cirrhosis": -0.23404228484790016,
            "d1_diasbp_invasive_max": -0.227208233962733,
            "d1_hematocrit_max": 0.21938270272530896,
            "h1_arterial_pco2_min": -0.2096593536126027,
            "lymphoma": -0.2037909456792066,
            "h1_sysbp_min": -0.19811244524016902,
            "d1_mbp_max": 0.19632381466021553,
            "d1_wbc_min": 0.1929838575361088,
            "d1_potassium_min": -0.19180334790973186,
            "h1_resprate_min": -0.1883094702261632,
            "intubated_apache": -0.185573453281526,
            "icu_admit_source": 0.184362163527128,
            "d1_sysbp_invasive_max": -0.18349750178821184,
            "d1_wbc_max": -0.18185865817162084,
            "renal_function_triad_flag": 0.180976939559561,
            "d1_diasbp_noninvasive_min": 0.17997144456791875,
            "d1_temp_min": 0.17762433829619734,
            "h1_diasbp_min": 0.16331302931691688,
            "h1_diasbp_invasive_min": 0.1605963511552683,
            "h1_diasbp_noninvasive_max": -0.1572483047750466,
            "d1_inr_max": -0.14926902649775772,
            "d1_platelets_min": 0.14790452538541807,
            "hematocrit_apache": -0.14681553332782193,
            "d1_spo2_max": -0.14563349923965088,
            "height": -0.14455877833937963,
            "h1_creatinine_max": 0.14140191835922872,
            "h1_hematocrit_min": 0.13860452619332383,
            "leukemia": 0.13419080053058788,
            "h1_arterial_ph_max": -0.12786202316289527,
            "d1_sysbp_max": 0.12624718187739292,
            "h1_arterial_pco2_max": 0.11186820259858886,
            "d1_hemaglobin_min": -0.11034809483839998,
            "icu_id": 0.10087002570705753,
            "heart_rate_apache": 0.09753648910840637,
            "d1_resprate_max": 0.09617895799309,
            "d1_lactate_max": 0.0819895962381124,
            "gcs_unable_apache": -0.07570852379344616,
            "h1_mbp_invasive_min": 0.06725502275551763,
            "h1_spo2_min": 0.06521062628988464,
            "ph_apache": 0.062312459112496936,
            "h1_albumin_min": -0.05861803328314684,
            "h1_diasbp_noninvasive_min": -0.05443093990423641,
            "h1_sysbp_noninvasive_min": 0.05357076942524852,
            "h1_hemaglobin_min": -0.05032124352329139,
            "h1_mbp_noninvasive_min": 0.0498251882420473,
            "d1_bun_max": 0.04790507254610585,
            "albumin_apache": 0.043314139746515115,
            "h1_lactate_min": -0.04320268462326719,
            "solid_tumor_with_metastasis": 0.042263882199390895,
            "d1_temp_max": -0.04220211693825352,
            "h1_mbp_min": 0.04142450845385581,
            "hospital_admit_source": 0.03908958833428664,
            "diabetes_mellitus": -0.03840441721917411,
            "paco2_apache": -0.030625298559288094,
            "d1_mbp_noninvasive_min": 0.01926733142102855,
            "age": 0.01740055428929252,
            "elective_surgery": 0.016874187545513907,
            "paco2_for_ph_apache": 0.014088419653858533,
            "d1_arterial_pco2_max": -0.013568899872154152,
            "fio2_apache": -0.012032102327827738,
            "d1_diasbp_noninvasive_max": 0.006093215132179133,
            "h1_diasbp_invasive_max": 0.003296725747065862
        },
        "Inherent": {
            "ventilated_apache": 45.08259601931911,
            "d1_bun_min": 23.932846130410734,
            "d1_sysbp_noninvasive_min": 13.098311066843788,
            "d1_resprate_max": 10.837712633694967,
            "gender": 0.0,
            "bmi": 0.0,
            "hospital_id": 0.0,
            "albumin_apache": 0.0,
            "icu_admit_source": 0.0,
            "icu_id": 0.0,
            "icu_stay_type": 0.0,
            "icu_type": 0.0,
            "pre_icu_los_days": 0.0,
            "readmission_status": 0.0,
            "weight": 0.0,
            "arf_apache": 0.0,
            "apache_2_diagnosis": 0.0,
            "apache_3j_diagnosis": 0.0,
            "apache_post_operative": 0.0,
            "bun_apache": 0.0,
            "ethnicity": 0.0,
            "height": 0.0,
            "elective_surgery": 0.0,
            "sodium_apache": 0.0,
            "fio2_apache": 0.0,
            "gcs_motor_apache": 0.0,
            "gcs_eyes_apache": 0.0,
            "gcs_verbal_apache": 0.0,
            "glucose_apache": 0.0,
            "heart_rate_apache": 0.0,
            "gcs_unable_apache": 0.0,
            "intubated_apache": 0.0,
            "map_apache": 0.0,
            "paco2_apache": 0.0,
            "paco2_for_ph_apache": 0.0,
            "pao2_apache": 0.0,
            "ph_apache": 0.0,
            "resprate_apache": 0.0,
            "hematocrit_apache": 0.0,
            "d1_diasbp_noninvasive_max": 0.0,
            "temp_apache": 0.0,
            "urineoutput_apache": 0.0,
            "wbc_apache": 0.0,
            "d1_diasbp_invasive_max": 0.0,
            "d1_diasbp_invasive_min": 0.0,
            "d1_diasbp_max": 0.0,
            "d1_diasbp_min": 0.0,
            "d1_mbp_invasive_max": 0.0,
            "d1_diasbp_noninvasive_min": 0.0,
            "d1_heartrate_max": 0.0,
            "d1_heartrate_min": 0.0,
            "d1_mbp_max": 0.0,
            "bilirubin_apache": 0.0,
            "creatinine_apache": 0.0,
            "hospital_admit_source": 0.0,
            "d1_potassium_max": 0.0,
            "d1_mbp_min": 0.0,
            "d1_mbp_invasive_min": 0.0,
            "d1_mbp_noninvasive_min": 0.0,
            "d1_spo2_max": 0.0,
            "d1_spo2_min": 0.0,
            "d1_sysbp_invasive_max": 0.0,
            "d1_mbp_noninvasive_max": 0.0,
            "d1_sysbp_invasive_min": 0.0,
            "d1_sysbp_max": 0.0,
            "d1_sysbp_min": 0.0,
            "d1_sysbp_noninvasive_max": 0.0,
            "d1_temp_max": 0.0,
            "d1_temp_min": 0.0,
            "h1_diasbp_invasive_max": 0.0,
            "d1_resprate_min": 0.0,
            "h1_diasbp_max": 0.0,
            "h1_diasbp_min": 0.0,
            "h1_diasbp_noninvasive_max": 0.0,
            "h1_diasbp_noninvasive_min": 0.0,
            "h1_heartrate_max": 0.0,
            "h1_heartrate_min": 0.0,
            "h1_mbp_invasive_max": 0.0,
            "h1_mbp_invasive_min": 0.0,
            "h1_mbp_max": 0.0,
            "h1_mbp_min": 0.0,
            "h1_mbp_noninvasive_max": 0.0,
            "h1_mbp_noninvasive_min": 0.0,
            "h1_resprate_max": 0.0,
            "h1_resprate_min": 0.0,
            "h1_spo2_max": 0.0,
            "h1_diasbp_invasive_min": 0.0,
            "h1_spo2_min": 0.0,
            "h1_sysbp_invasive_max": 0.0,
            "h1_sysbp_max": 0.0,
            "h1_sysbp_invasive_min": 0.0,
            "h1_sysbp_noninvasive_max": 0.0,
            "h1_sysbp_noninvasive_min": 0.0,
            "h1_temp_max": 0.0,
            "h1_sysbp_min": 0.0,
            "h1_temp_min": 0.0,
            "d1_albumin_max": 0.0,
            "d1_bilirubin_max": 0.0,
            "d1_albumin_min": 0.0,
            "d1_bilirubin_min": 0.0,
            "d1_bun_max": 0.0,
            "d1_calcium_max": 0.0,
            "d1_calcium_min": 0.0,
            "d1_creatinine_max": 0.0,
            "d1_creatinine_min": 0.0,
            "d1_glucose_max": 0.0,
            "d1_glucose_min": 0.0,
            "d1_hco3_max": 0.0,
            "d1_hco3_min": 0.0,
            "d1_hemaglobin_max": 0.0,
            "d1_hemaglobin_min": 0.0,
            "d1_hematocrit_max": 0.0,
            "d1_hematocrit_min": 0.0,
            "d1_inr_max": 0.0,
            "d1_inr_min": 0.0,
            "d1_lactate_max": 0.0,
            "d1_lactate_min": 0.0,
            "d1_platelets_max": 0.0,
            "d1_platelets_min": 0.0,
            "h1_sodium_max": 0.0,
            "d1_potassium_min": 0.0,
            "d1_sodium_max": 0.0,
            "d1_sodium_min": 0.0,
            "d1_wbc_max": 0.0,
            "d1_wbc_min": 0.0,
            "h1_albumin_max": 0.0,
            "h1_albumin_min": 0.0,
            "h1_bilirubin_max": 0.0,
            "h1_bilirubin_min": 0.0,
            "h1_bun_max": 0.0,
            "h1_bun_min": 0.0,
            "h1_calcium_max": 0.0,
            "h1_calcium_min": 0.0,
            "h1_creatinine_max": 0.0,
            "h1_creatinine_min": 0.0,
            "h1_glucose_max": 0.0,
            "h1_glucose_min": 0.0,
            "h1_hco3_max": 0.0,
            "h1_hco3_min": 0.0,
            "h1_hemaglobin_max": 0.0,
            "h1_hemaglobin_min": 0.0,
            "h1_hematocrit_max": 0.0,
            "h1_hematocrit_min": 0.0,
            "h1_inr_max": 0.0,
            "h1_inr_min": 0.0,
            "h1_lactate_max": 0.0,
            "h1_lactate_min": 0.0,
            "h1_platelets_max": 0.0,
            "h1_platelets_min": 0.0,
            "h1_potassium_max": 0.0,
            "h1_potassium_min": 0.0,
            "h1_arterial_po2_max": 0.0,
            "h1_sodium_min": 0.0,
            "h1_wbc_max": 0.0,
            "h1_wbc_min": 0.0,
            "d1_arterial_pco2_max": 0.0,
            "d1_arterial_pco2_min": 0.0,
            "d1_arterial_ph_max": 0.0,
            "d1_arterial_ph_min": 0.0,
            "d1_arterial_po2_max": 0.0,
            "d1_arterial_po2_min": 0.0,
            "d1_pao2fio2ratio_max": 0.0,
            "d1_pao2fio2ratio_min": 0.0,
            "h1_arterial_pco2_max": 0.0,
            "h1_arterial_pco2_min": 0.0,
            "h1_arterial_ph_max": 0.0,
            "h1_arterial_ph_min": 0.0,
            "immunosuppression": 0.0,
            "h1_arterial_po2_min": 0.0,
            "h1_pao2fio2ratio_max": 0.0,
            "h1_pao2fio2ratio_min": 0.0,
            "aids": 0.0,
            "cirrhosis": 0.0,
            "diabetes_mellitus": 0.0,
            "hepatic_failure": 0.0,
            "apache_3j_bodysystem": 0.0,
            "leukemia": 0.0,
            "lymphoma": 0.0,
            "solid_tumor_with_metastasis": 0.0,
            "renal_function_triad_flag": 0.0,
            "apache_2_bodysystem": 0.0,
            "mods_pentad_flag": 0.0,
            "age": -7.048534149731389
        }
    },
    "XGBOOST": {
        "SHAP": {
            "ventilated_apache": -7.493644714355469,
            "d1_heartrate_max": -4.936637878417969,
            "d1_bun_max": -4.525209903717041,
            "gcs_motor_apache": -2.8469326496124268,
            "d1_resprate_max": -2.7433338165283203,
            "age": 2.7156848907470703,
            "d1_bun_min": -2.3788464069366455,
            "d1_heartrate_min": -2.370424509048462,
            "d1_spo2_min": -2.303539514541626,
            "gcs_verbal_apache": -2.2975478172302246,
            "heart_rate_apache": -2.2091898918151855,
            "d1_hemaglobin_min": -2.107252836227417,
            "d1_bilirubin_max": -1.8702898025512695,
            "d1_glucose_min": -1.7820073366165161,
            "apache_3j_bodysystem": 1.743578553199768,
            "bmi": -1.7113394737243652,
            "h1_glucose_max": -1.66131591796875,
            "hospital_id": 1.6023499965667725,
            "d1_wbc_min": -1.565063238143921,
            "d1_resprate_min": -1.472425937652588,
            "resprate_apache": -1.4576420783996582,
            "d1_sysbp_min": -1.4016627073287964,
            "bilirubin_apache": -1.3432931900024414,
            "d1_temp_max": -1.2547235488891602,
            "h1_glucose_min": -1.2372020483016968,
            "d1_platelets_min": -1.1702169179916382,
            "d1_bilirubin_min": -1.1292815208435059,
            "gcs_eyes_apache": -1.1158778667449951,
            "h1_heartrate_max": 1.0795845985412598,
            "d1_albumin_min": -1.0708380937576294,
            "d1_calcium_max": -1.0657484531402588,
            "h1_temp_min": 1.047437310218811,
            "d1_wbc_max": -1.0314240455627441,
            "wbc_apache": -0.9721214771270752,
            "d1_lactate_min": -0.8771045804023743,
            "d1_hemaglobin_max": -0.869976282119751,
            "d1_arterial_ph_min": -0.8349577784538269,
            "urineoutput_apache": 0.8346559405326843,
            "pre_icu_los_days": -0.8182939887046814,
            "apache_2_bodysystem": 0.809098482131958,
            "d1_arterial_pco2_min": -0.7762032747268677,
            "d1_creatinine_min": 0.7715475559234619,
            "d1_albumin_max": -0.7269315719604492,
            "d1_sodium_min": -0.6963419318199158,
            "d1_creatinine_max": -0.6833040118217468,
            "glucose_apache": -0.6664363741874695,
            "map_apache": -0.6640638709068298,
            "h1_temp_max": 0.6536362767219543,
            "temp_apache": 0.616626501083374,
            "h1_resprate_min": -0.6143336296081543,
            "icu_type": -0.5692766904830933,
            "apache_2_diagnosis": -0.562368631362915,
            "d1_sysbp_max": -0.5265998244285583,
            "h1_diasbp_max": -0.5257796049118042,
            "d1_pao2fio2ratio_min": -0.5231824517250061,
            "creatinine_apache": -0.5074266195297241,
            "h1_spo2_max": -0.4915159344673157,
            "d1_arterial_pco2_max": -0.4528489410877228,
            "h1_heartrate_min": 0.4327695369720459,
            "h1_creatinine_max": 0.429522842168808,
            "apache_3j_diagnosis": -0.42270058393478394,
            "elective_surgery": 0.40676310658454895,
            "d1_calcium_min": -0.40094074606895447,
            "height": -0.39702871441841125,
            "d1_pao2fio2ratio_max": -0.3855879008769989,
            "bun_apache": -0.3802545666694641,
            "d1_hco3_max": -0.37879425287246704,
            "d1_glucose_max": -0.36306318640708923,
            "d1_arterial_po2_min": -0.35867100954055786,
            "albumin_apache": -0.34933745861053467,
            "h1_diasbp_noninvasive_max": -0.3467068374156952,
            "d1_lactate_max": -0.3459188640117645,
            "d1_arterial_ph_max": -0.3447331190109253,
            "d1_platelets_max": -0.3395586907863617,
            "d1_sysbp_noninvasive_max": -0.33874276280403137,
            "d1_sysbp_invasive_max": -0.32247865200042725,
            "h1_resprate_max": -0.31536179780960083,
            "h1_mbp_max": -0.30509504675865173,
            "h1_hco3_max": -0.2964637577533722,
            "sodium_apache": -0.26545974612236023,
            "d1_potassium_max": -0.26150694489479065,
            "d1_arterial_po2_max": -0.255490243434906,
            "d1_inr_max": -0.2539569139480591,
            "fio2_apache": -0.2534319758415222,
            "icu_admit_source": -0.24256226420402527,
            "d1_mbp_invasive_min": -0.22568516433238983,
            "hospital_admit_source": 0.21898238360881805,
            "h1_hco3_min": -0.2180488556623459,
            "d1_hematocrit_max": 0.21691028773784637,
            "h1_bilirubin_max": -0.2145838886499405,
            "d1_sysbp_invasive_min": -0.201570063829422,
            "h1_albumin_max": -0.1812611222267151,
            "h1_mbp_noninvasive_min": 0.18118339776992798,
            "solid_tumor_with_metastasis": -0.1733696460723877,
            "d1_diasbp_invasive_min": -0.15264539420604706,
            "h1_diasbp_min": -0.15046902000904083,
            "gender": -0.14736329019069672,
            "h1_sysbp_noninvasive_min": 0.14457440376281738,
            "hematocrit_apache": -0.14457184076309204,
            "gcs_unable_apache": -0.136760413646698,
            "h1_sysbp_max": 0.1269332319498062,
            "d1_hematocrit_min": -0.12644052505493164,
            "h1_creatinine_min": -0.11782118678092957,
            "arf_apache": -0.1158425435423851,
            "h1_spo2_min": 0.11334000527858734,
            "d1_mbp_min": -0.10956887900829315,
            "h1_diasbp_noninvasive_min": -0.10662280023097992,
            "d1_potassium_min": 0.10298226028680801,
            "d1_diasbp_noninvasive_min": -0.10201829671859741,
            "h1_sysbp_noninvasive_max": 0.10186613351106644,
            "h1_mbp_noninvasive_max": -0.09738509356975555,
            "d1_temp_min": 0.09679391235113144,
            "ethnicity": 0.09414976835250854,
            "d1_mbp_noninvasive_max": -0.09178272634744644,
            "h1_bun_min": -0.08676687628030777,
            "immunosuppression": -0.0830412283539772,
            "d1_diasbp_invasive_max": -0.07793620973825455,
            "d1_sodium_max": 0.07649003714323044,
            "h1_albumin_min": -0.0730929747223854,
            "h1_sodium_max": -0.06723660975694656,
            "h1_arterial_po2_min": 0.06407114863395691,
            "ph_apache": -0.06401389837265015,
            "weight": -0.0633581280708313,
            "d1_sysbp_noninvasive_min": -0.060881517827510834,
            "d1_diasbp_noninvasive_max": -0.05407537519931793,
            "d1_mbp_invasive_max": -0.050048280507326126,
            "d1_diasbp_min": -0.049938466399908066,
            "diabetes_mellitus": 0.04784160479903221,
            "h1_hematocrit_min": 0.04585949331521988,
            "h1_mbp_invasive_min": -0.044586632400751114,
            "h1_arterial_ph_max": 0.04279607906937599,
            "h1_bun_max": -0.04123475402593613,
            "h1_potassium_min": -0.040223684161901474,
            "h1_pao2fio2ratio_min": 0.03908433020114899,
            "h1_calcium_max": 0.036966435611248016,
            "h1_inr_min": -0.03623402863740921,
            "h1_hemaglobin_min": 0.03598571568727493,
            "icu_id": 0.03196942061185837,
            "h1_platelets_max": -0.02902413159608841,
            "h1_sysbp_min": 0.025797825306653976,
            "d1_mbp_max": 0.02546701207756996,
            "h1_diasbp_invasive_max": -0.02506478875875473,
            "h1_arterial_po2_max": 0.024953298270702362,
            "h1_inr_max": -0.024681134149432182,
            "apache_post_operative": 0.024523146450519562,
            "renal_function_triad_flag": -0.024328332394361496,
            "intubated_apache": -0.021279223263263702,
            "d1_hco3_min": 0.01943199150264263,
            "paco2_apache": 0.019265083596110344,
            "h1_sysbp_invasive_max": 0.018298981711268425,
            "paco2_for_ph_apache": 0.01733611337840557,
            "hepatic_failure": -0.016923049464821815,
            "h1_hemaglobin_max": 0.016717173159122467,
            "d1_inr_min": -0.015347535721957684,
            "h1_diasbp_invasive_min": -0.014651760458946228,
            "h1_lactate_max": 0.013018463738262653,
            "d1_mbp_noninvasive_min": 0.011315909214317799,
            "h1_sodium_min": -0.010508490726351738,
            "h1_platelets_min": -0.009806727059185505,
            "h1_wbc_min": 0.009146353229880333,
            "h1_lactate_min": 0.009012047201395035,
            "h1_mbp_min": -0.008779744617640972,
            "h1_pao2fio2ratio_max": 0.007910529151558876,
            "h1_calcium_min": 0.007665711920708418,
            "h1_bilirubin_min": -0.007210579700767994,
            "d1_spo2_max": 0.007165688090026379,
            "h1_arterial_ph_min": -0.006952814757823944,
            "h1_sysbp_invasive_min": 0.00679349759593606,
            "pao2_apache": 0.0041525219567120075,
            "h1_wbc_max": 0.0036069005727767944,
            "d1_diasbp_max": -0.0022966410033404827,
            "h1_mbp_invasive_max": 0.00196306430734694,
            "h1_hematocrit_max": -0.0016539809294044971,
            "h1_potassium_max": 0.0008330261916853487,
            "icu_stay_type": 0.0007738839485682547,
            "h1_arterial_pco2_min": 0.0005181603482924402,
            "lymphoma": -0.00046875467523932457,
            "h1_arterial_pco2_max": -0.00043432164238765836,
            "cirrhosis": -0.0003098980523645878,
            "leukemia": -0.0001587218139320612,
            "aids": -9.608223626855761e-05,
            "mods_pentad_flag": 1.9780123693635687e-05,
            "readmission_status": 0.0
        },
        "Lime": {
            "age": 4.724061488689388,
            "pre_icu_los_days": 4.53584768281595,
            "d1_lactate_min": 3.770107746205028,
            "d1_bun_max": 3.7329491737443368,
            "urineoutput_apache": -2.785643664645716,
            "d1_spo2_min": -2.4158036489865626,
            "d1_heartrate_max": 2.1016522829279682,
            "d1_resprate_max": 1.9450978524687765,
            "d1_bun_min": 1.658193287984494,
            "apache_2_diagnosis": 1.6417945779445438,
            "d1_resprate_min": 1.4853384725988465,
            "d1_mbp_min": -1.3218868553137182,
            "d1_platelets_min": -1.321380773604208,
            "weight": -1.24879534795193,
            "bmi": -1.2102924868918765,
            "d1_wbc_min": 1.1900245516862786,
            "d1_sysbp_min": -1.1764094083409498,
            "d1_lactate_max": 1.1380657560077496,
            "apache_3j_diagnosis": -1.1312465572723016,
            "d1_heartrate_min": 1.1279658908152848,
            "d1_albumin_min": -1.0307016500146557,
            "h1_glucose_max": 0.9738673457459421,
            "ethnicity": 0.8908010997351725,
            "d1_platelets_max": -0.8616499043028318,
            "d1_arterial_ph_min": -0.8449950084044431,
            "d1_pao2fio2ratio_max": -0.8332050475947219,
            "h1_potassium_min": -0.7979451367945435,
            "h1_arterial_ph_min": -0.7967111520109837,
            "d1_potassium_max": 0.7963966088542144,
            "bun_apache": 0.7900592523461545,
            "d1_sodium_min": -0.7769514126817617,
            "d1_hco3_min": -0.7677498038460833,
            "h1_mbp_noninvasive_min": -0.7669647984832679,
            "h1_glucose_min": 0.7631760929480597,
            "d1_temp_min": -0.7613138823302446,
            "d1_bilirubin_min": 0.7592281846681276,
            "h1_arterial_po2_min": 0.734548297263638,
            "h1_wbc_max": 0.727807749077087,
            "ventilated_apache": 0.7068111609140272,
            "apache_3j_bodysystem": 0.6827649101109203,
            "gcs_eyes_apache": -0.6813951928148949,
            "h1_hco3_max": 0.6610104696521084,
            "wbc_apache": 0.6561507953142549,
            "elective_surgery": -0.650872663394129,
            "d1_spo2_max": -0.6324113505889154,
            "creatinine_apache": 0.6280381823675999,
            "icu_admit_source": 0.6205518574844433,
            "gcs_unable_apache": 0.6204869407410486,
            "h1_sysbp_invasive_max": -0.6172065352355974,
            "h1_mbp_invasive_min": 0.6113773195157985,
            "h1_temp_min": -0.6028423568208114,
            "bilirubin_apache": 0.5927409332133805,
            "d1_hco3_max": -0.5887743204425162,
            "hematocrit_apache": 0.5761527280784519,
            "d1_wbc_max": 0.5747410601515888,
            "d1_hemaglobin_max": -0.5715634399878149,
            "d1_bilirubin_max": 0.5474194313770137,
            "h1_diasbp_noninvasive_min": -0.5403380366149526,
            "gcs_verbal_apache": -0.5355120097991104,
            "h1_sysbp_noninvasive_max": 0.5311609351255784,
            "h1_albumin_min": -0.5273544596306501,
            "h1_spo2_max": 0.5244815033112973,
            "resprate_apache": 0.5228691671761464,
            "d1_diasbp_invasive_max": 0.5209452611006047,
            "h1_platelets_max": 0.5140544354894158,
            "d1_creatinine_max": 0.5085561618714489,
            "d1_arterial_po2_max": 0.5059238590220548,
            "renal_function_triad_flag": -0.5050950811680217,
            "h1_sysbp_min": -0.49008410911185707,
            "h1_hemaglobin_min": -0.47013853146209766,
            "apache_post_operative": 0.47006316367820544,
            "d1_diasbp_max": -0.46850451022884465,
            "d1_hematocrit_min": 0.4624598447690096,
            "h1_diasbp_invasive_max": -0.462312295175597,
            "h1_mbp_min": -0.46009399529756145,
            "d1_sodium_max": 0.4557981331707502,
            "d1_arterial_ph_max": 0.44589883851446493,
            "sodium_apache": 0.4438684676588634,
            "h1_lactate_max": -0.43462547028556175,
            "h1_bun_min": -0.43426910373741284,
            "h1_hematocrit_min": -0.42532010584728974,
            "h1_inr_max": -0.4249808062773113,
            "d1_glucose_min": 0.42393130100172605,
            "d1_sysbp_noninvasive_max": 0.41672832696715834,
            "d1_mbp_noninvasive_max": 0.4117161269813832,
            "icu_stay_type": -0.4090955827689986,
            "fio2_apache": 0.40779447376035505,
            "hospital_id": 0.40151999906708247,
            "h1_sysbp_max": 0.398406201286229,
            "h1_arterial_ph_max": -0.3941660444553163,
            "temp_apache": -0.38587251651231436,
            "h1_diasbp_noninvasive_max": 0.3799273737419959,
            "h1_pao2fio2ratio_min": 0.37807051282179166,
            "d1_sysbp_max": -0.35409366640252793,
            "pao2_apache": -0.3386530131471448,
            "d1_diasbp_noninvasive_min": 0.33633896273370845,
            "d1_calcium_min": 0.33426743062401826,
            "h1_arterial_pco2_max": -0.326970512910065,
            "h1_platelets_min": 0.3151155913501609,
            "h1_arterial_po2_max": -0.3141652993030901,
            "h1_sodium_min": 0.3117939151058537,
            "h1_bilirubin_min": 0.30937170064417985,
            "apache_2_bodysystem": 0.3048535919789058,
            "d1_diasbp_min": -0.29988680894828784,
            "h1_bilirubin_max": 0.2904046826126765,
            "d1_inr_min": 0.2822584130196439,
            "h1_sysbp_noninvasive_min": 0.28220760237068165,
            "h1_heartrate_max": 0.2771886112992152,
            "h1_mbp_invasive_max": -0.27595983915697997,
            "d1_arterial_pco2_max": 0.27445145853647,
            "cirrhosis": 0.26975813159134376,
            "h1_hco3_min": -0.26839613435134585,
            "h1_diasbp_min": -0.25617582535559075,
            "diabetes_mellitus": 0.25584913601584647,
            "leukemia": 0.25018253749929653,
            "hepatic_failure": -0.2493561677409481,
            "d1_mbp_max": -0.23941564370340487,
            "intubated_apache": -0.23777330619298911,
            "d1_sysbp_noninvasive_min": -0.2335907321477407,
            "h1_inr_min": -0.2322737566842327,
            "immunosuppression": 0.22968908777275993,
            "readmission_status": 0.22934424382862806,
            "h1_arterial_pco2_min": 0.22455344548024891,
            "h1_bun_max": 0.21903203010886435,
            "h1_calcium_min": -0.21851161358906146,
            "d1_mbp_invasive_max": -0.21806198360717505,
            "d1_arterial_po2_min": -0.21301591632554448,
            "h1_heartrate_min": -0.21252535160102065,
            "h1_mbp_max": 0.21251976171771506,
            "h1_mbp_noninvasive_max": 0.21138570517455357,
            "d1_mbp_noninvasive_min": -0.20331172094193792,
            "h1_creatinine_max": -0.20244715605219343,
            "d1_calcium_max": 0.19659247217639228,
            "h1_sysbp_invasive_min": -0.19266377468053839,
            "d1_pao2fio2ratio_min": -0.19001859735923468,
            "d1_glucose_max": -0.18193248599786277,
            "d1_hemaglobin_min": -0.18073652237233334,
            "heart_rate_apache": 0.1776900468642642,
            "height": 0.15785354838611432,
            "ph_apache": 0.15665975376177246,
            "mods_pentad_flag": -0.15126779719494873,
            "d1_potassium_min": -0.14954557173863173,
            "icu_type": 0.14648875233547767,
            "h1_diasbp_invasive_min": -0.14579619545447003,
            "albumin_apache": 0.1452170810034625,
            "gender": 0.14404051234334336,
            "h1_hemaglobin_max": -0.1369014300803898,
            "h1_sodium_max": 0.1361920943305876,
            "h1_temp_max": 0.13551592882617292,
            "lymphoma": -0.13234465334434053,
            "h1_creatinine_min": -0.13229367674957473,
            "solid_tumor_with_metastasis": 0.12777991007911935,
            "arf_apache": -0.11764551321961005,
            "hospital_admit_source": -0.11550210322492846,
            "d1_albumin_max": -0.1121432860356259,
            "d1_arterial_pco2_min": -0.10930421521948339,
            "d1_inr_max": 0.10848754018263794,
            "gcs_motor_apache": -0.107195962348716,
            "h1_pao2fio2ratio_max": -0.10689644265367967,
            "map_apache": 0.09992286066686398,
            "paco2_for_ph_apache": 0.09239077241408081,
            "d1_sysbp_invasive_min": -0.08590443710783144,
            "h1_calcium_max": 0.07908736614421838,
            "h1_hematocrit_max": -0.07876143541816845,
            "h1_diasbp_max": -0.07674462742249344,
            "glucose_apache": -0.07225521294217441,
            "h1_resprate_max": 0.06392429848343424,
            "aids": -0.05348916577022248,
            "h1_resprate_min": 0.052187539345259285,
            "d1_hematocrit_max": 0.047459796595197196,
            "d1_sysbp_invasive_max": -0.04727934288996024,
            "h1_wbc_min": 0.03875141022243214,
            "h1_lactate_min": -0.03724663031059503,
            "d1_diasbp_invasive_min": -0.03670502384366676,
            "d1_temp_max": 0.031856742581991726,
            "d1_mbp_invasive_min": -0.02892445809156429,
            "h1_potassium_max": -0.027851892902368107,
            "d1_diasbp_noninvasive_max": 0.02672358563969079,
            "d1_creatinine_min": -0.02597962622957519,
            "h1_albumin_max": -0.019377817578666454,
            "h1_spo2_min": 0.011017813764963953,
            "icu_id": 0.0030229095221537233,
            "paco2_apache": 0.0014005514310440278
        },
        "Inherent": {
            "ventilated_apache": 15.33239995417795,
            "gcs_motor_apache": 4.658391344423496,
            "elective_surgery": 2.886161286732242,
            "apache_post_operative": 2.4147896015072687,
            "gcs_verbal_apache": 2.060749510353054,
            "gcs_eyes_apache": 2.026725695635516,
            "d1_bun_max": 1.8761187052085004,
            "d1_sysbp_min": 1.7568339217558677,
            "d1_lactate_min": 1.6624640124361125,
            "d1_bun_min": 1.541080431264725,
            "apache_3j_diagnosis": 1.2054154330021554,
            "d1_spo2_min": 1.1796153762149038,
            "d1_arterial_ph_min": 1.0198019484645402,
            "d1_sysbp_noninvasive_min": 1.0020395001739837,
            "solid_tumor_with_metastasis": 0.962999343821478,
            "age": 0.919016003764195,
            "d1_lactate_max": 0.873173433446211,
            "d1_albumin_min": 0.8171331146250833,
            "d1_pao2fio2ratio_min": 0.8136518867341758,
            "d1_temp_min": 0.7899148269764366,
            "d1_arterial_pco2_min": 0.7746959964308553,
            "d1_heartrate_max": 0.7400559994947151,
            "gcs_unable_apache": 0.738739369008324,
            "d1_pao2fio2ratio_max": 0.6767511831084199,
            "d1_resprate_max": 0.6533203395226995,
            "apache_3j_bodysystem": 0.6166748672178262,
            "h1_inr_min": 0.5907929499612989,
            "icu_admit_source": 0.5898779805674567,
            "d1_resprate_min": 0.5835704439160235,
            "d1_platelets_min": 0.5771396212942246,
            "d1_heartrate_min": 0.5757233007462866,
            "h1_resprate_min": 0.5686942670028564,
            "d1_inr_max": 0.5255767588321452,
            "d1_inr_min": 0.5232444429812859,
            "h1_inr_max": 0.5217177487669087,
            "d1_bilirubin_min": 0.5135276689553567,
            "d1_mbp_min": 0.5107065604925768,
            "pre_icu_los_days": 0.5026975713215708,
            "apache_2_diagnosis": 0.49673350195457977,
            "fio2_apache": 0.49549522969612564,
            "renal_function_triad_flag": 0.4918432763839884,
            "bun_apache": 0.47594536478040417,
            "urineoutput_apache": 0.46440979546195993,
            "d1_bilirubin_max": 0.4554151199230051,
            "d1_temp_max": 0.43480527867153923,
            "d1_wbc_min": 0.4307389642199776,
            "d1_mbp_noninvasive_min": 0.4262317564976359,
            "d1_creatinine_max": 0.4209017343176939,
            "apache_2_bodysystem": 0.4188272754074362,
            "d1_albumin_max": 0.41271207902024365,
            "d1_arterial_po2_min": 0.4041888263912154,
            "d1_sodium_max": 0.40204340287362517,
            "d1_hemaglobin_min": 0.3993813103181033,
            "d1_sysbp_noninvasive_max": 0.3970697249058766,
            "icu_type": 0.391602124780812,
            "bmi": 0.3890811831641019,
            "albumin_apache": 0.38448309404782344,
            "d1_sysbp_max": 0.3782801647462817,
            "immunosuppression": 0.376214266870408,
            "heart_rate_apache": 0.37554342846121264,
            "d1_arterial_pco2_max": 0.3738711612861309,
            "d1_wbc_max": 0.36919032729619805,
            "d1_arterial_ph_max": 0.36672754411141956,
            "d1_hco3_min": 0.3573040739535829,
            "d1_sysbp_invasive_max": 0.3571516026387259,
            "bilirubin_apache": 0.3547290775412577,
            "creatinine_apache": 0.35169988641629946,
            "icu_id": 0.3503186236579261,
            "d1_sysbp_invasive_min": 0.3455532052332316,
            "temp_apache": 0.3412666033390681,
            "d1_creatinine_min": 0.3393648155396727,
            "resprate_apache": 0.33868722028102544,
            "h1_temp_max": 0.33589137040729605,
            "h1_temp_min": 0.3347912067365917,
            "d1_mbp_invasive_min": 0.3317898566614693,
            "d1_diasbp_noninvasive_min": 0.32848642942681944,
            "d1_diasbp_invasive_max": 0.32098809534397116,
            "d1_hco3_max": 0.3197171001235117,
            "d1_platelets_max": 0.31915893483213986,
            "d1_sodium_min": 0.31836516421433014,
            "wbc_apache": 0.31749908469453253,
            "d1_diasbp_invasive_min": 0.3147821236913672,
            "hospital_admit_source": 0.3106955033152748,
            "d1_glucose_min": 0.3106346916702077,
            "d1_hemaglobin_max": 0.30977214976792417,
            "h1_diasbp_invasive_min": 0.30959105912737833,
            "h1_resprate_max": 0.3078317665614502,
            "weight": 0.30501773333369847,
            "h1_mbp_invasive_min": 0.3033925518477292,
            "glucose_apache": 0.3007603167840261,
            "d1_diasbp_min": 0.2987832838601062,
            "d1_spo2_max": 0.297684676741108,
            "intubated_apache": 0.2974087071988345,
            "d1_arterial_po2_max": 0.2942201464048669,
            "h1_glucose_min": 0.29401984650121954,
            "lymphoma": 0.2917858764172519,
            "d1_potassium_min": 0.28997619048983564,
            "d1_mbp_noninvasive_max": 0.2895401968193126,
            "d1_glucose_max": 0.2882713949217119,
            "hepatic_failure": 0.2860764801350997,
            "arf_apache": 0.28584133469893863,
            "paco2_apache": 0.2857087094183357,
            "h1_mbp_noninvasive_min": 0.28548948326098805,
            "h1_sysbp_noninvasive_min": 0.2842386701484465,
            "h1_creatinine_min": 0.28172961492658377,
            "map_apache": 0.280819651261524,
            "h1_arterial_ph_min": 0.2796189485010694,
            "h1_glucose_max": 0.27944930205318164,
            "h1_mbp_invasive_max": 0.27934984193677315,
            "h1_diasbp_invasive_max": 0.27891611234145913,
            "h1_arterial_ph_max": 0.2773752145927628,
            "h1_sysbp_invasive_min": 0.27614753749876336,
            "h1_mbp_min": 0.2761195903204021,
            "hospital_id": 0.2756017008044281,
            "ph_apache": 0.27514398616236857,
            "diabetes_mellitus": 0.2749230796367017,
            "cirrhosis": 0.2747212408694358,
            "h1_sysbp_invasive_max": 0.27359132583543794,
            "h1_heartrate_max": 0.2730615853007917,
            "d1_calcium_max": 0.2728691035318505,
            "d1_calcium_min": 0.27216699258383065,
            "h1_spo2_max": 0.27176267827814626,
            "h1_wbc_min": 0.2709195048317523,
            "h1_sysbp_min": 0.2706661406653938,
            "hematocrit_apache": 0.27020419857040495,
            "h1_hematocrit_min": 0.2696038118140025,
            "h1_sysbp_noninvasive_max": 0.26958255073274284,
            "h1_arterial_po2_max": 0.26916021226582415,
            "d1_hematocrit_max": 0.2687591171920775,
            "d1_hematocrit_min": 0.26811495241893835,
            "h1_platelets_min": 0.26752712420471086,
            "paco2_for_ph_apache": 0.26732576301580935,
            "h1_creatinine_max": 0.2665882405164735,
            "h1_albumin_min": 0.2653970362590442,
            "icu_stay_type": 0.26411762150890133,
            "h1_hco3_min": 0.26372602493818004,
            "h1_hemaglobin_min": 0.2634779848861801,
            "d1_diasbp_noninvasive_max": 0.26344688922823134,
            "h1_diasbp_noninvasive_min": 0.26290791551187337,
            "h1_heartrate_min": 0.2619408193239612,
            "h1_lactate_min": 0.26175769455334474,
            "h1_hematocrit_max": 0.2615415284351468,
            "sodium_apache": 0.25978280188802083,
            "h1_bun_min": 0.25943958223680463,
            "h1_calcium_min": 0.259119392475605,
            "h1_pao2fio2ratio_min": 0.2584743432980873,
            "h1_mbp_noninvasive_max": 0.2569605967638116,
            "pao2_apache": 0.2568181899707822,
            "h1_calcium_max": 0.25616903715694817,
            "d1_potassium_max": 0.2559848511010775,
            "leukemia": 0.2547974674705634,
            "d1_mbp_invasive_max": 0.2544302273964265,
            "h1_sysbp_max": 0.252990753141859,
            "h1_hemaglobin_max": 0.25213954930370813,
            "h1_sodium_max": 0.25009526627084555,
            "h1_arterial_po2_min": 0.24978110814750745,
            "h1_potassium_min": 0.24904441698828744,
            "gender": 0.2489323452654413,
            "h1_diasbp_min": 0.248927870179286,
            "h1_wbc_max": 0.24879036298651364,
            "h1_lactate_max": 0.24866960641267044,
            "h1_arterial_pco2_max": 0.24782710511360423,
            "h1_potassium_max": 0.24763085578201052,
            "h1_albumin_max": 0.2475450862453816,
            "h1_diasbp_noninvasive_max": 0.24617371112796013,
            "h1_diasbp_max": 0.2456446958049043,
            "height": 0.24460124014295065,
            "d1_mbp_max": 0.24336930021984668,
            "h1_bun_max": 0.24335115224199946,
            "h1_sodium_min": 0.24330962061238412,
            "h1_pao2fio2ratio_max": 0.24208123599488185,
            "ethnicity": 0.240921675726116,
            "h1_arterial_pco2_min": 0.24087662416707417,
            "d1_diasbp_max": 0.2387966996377572,
            "h1_hco3_max": 0.23841058637418272,
            "h1_platelets_max": 0.23685083312413638,
            "h1_bilirubin_min": 0.23680988520141086,
            "h1_mbp_max": 0.23643815235303112,
            "h1_bilirubin_max": 0.23295200717377895,
            "h1_spo2_min": 0.22200575186891808,
            "aids": 0.1925053117857617,
            "mods_pentad_flag": 0.1924144834560876
        }
    }
}